desc_stats.py
desc_stats-0.0.2.dist-info/LICENSE
desc_stats-0.0.2.dist-info/METADATA
desc_stats-0.0.2.dist-info/WHEEL
desc_stats-0.0.2.dist-info/top_level.txt
desc_stats-0.0.2.dist-info/RECORD
