Metadata-Version: 2.1
Name: desc-stats
Version: 0.0.2
Summary: Descriptive Statistics comprises of Measures of Central Tendency, Dispersion, Symmetry, Association, Normal Distribution, Misc.
Home-page: https://github.com/vinayvinu500/desc_stats
Author: Vinay Govardhanam
Author-email: vinayvinu500@gmail.com
Classifier: Programming Language :: Python :: 3
Classifier: Programming Language :: Python :: 3.8
Classifier: Programming Language :: Python :: 3.9
Classifier: Programming Language :: Python :: 3.10
Classifier: Programming Language :: Python :: 3.11
Classifier: License :: OSI Approved :: MIT License
Classifier: Operating System :: OS Independent
License-File: LICENSE
Requires-Dist: numpy
Requires-Dist: pandas
Requires-Dist: scipy
Requires-Dist: statsmodels
Provides-Extra: dev
Requires-Dist: pytest ; extra == 'dev'
Requires-Dist: twine ; extra == 'dev'
